taggin/__init__.py
taggin/cli.py
taggin/log.py
taggin-0.1.2.dist-info/METADATA
taggin-0.1.2.dist-info/WHEEL
taggin-0.1.2.dist-info/entry_points.txt
taggin-0.1.2.dist-info/RECORD
