Metadata-Version: 2.4
Name: taggin
Version: 0.1.2
Summary: Taggin logging with dynamic tags, structured storage, and CLI search.
Author-email: ESPR3SS0 <98864173+ESPR3SS0@users.noreply.github.com>
License: MIT
Classifier: License :: OSI Approved :: MIT License
Classifier: Operating System :: OS Independent
Classifier: Programming Language :: Python :: 3
Classifier: Programming Language :: Python :: 3 :: Only
Classifier: Programming Language :: Python :: 3.10
Classifier: Programming Language :: Python :: 3.11
Classifier: Programming Language :: Python :: 3.12
Requires-Python: >=3.10
Requires-Dist: arrow>=1.4.0
Requires-Dist: cyclopts>=4.2.4
Requires-Dist: pandas>=2.3
Requires-Dist: rich>=13.9.2
Provides-Extra: dev
Requires-Dist: mkdocs>=1.6.0; extra == 'dev'
Requires-Dist: pytest>=9.0.1; extra == 'dev'
